misfit_toys/__init__.py
misfit_toys/swiffer.py
misfit_toys/utils.py
misfit_toys/beta/__init__.py
misfit_toys/beta/helpers.py
misfit_toys/beta/main.py
misfit_toys/beta/plotter.py
misfit_toys/beta/w2.py
misfit_toys/beta/data/__init__.py
misfit_toys/beta/data/gauss.py
misfit_toys/data/__init__.py
misfit_toys/data/dataset.py
misfit_toys/data/download_data.py
misfit_toys/data/custom/factory.py
misfit_toys/data/custom/metadata.py
misfit_toys/data/das_curtin/__init__.py
misfit_toys/data/das_curtin/factory.py
misfit_toys/data/das_curtin/metadata.py
misfit_toys/data/marmousi/__init__.py
misfit_toys/data/marmousi/factory.py
misfit_toys/data/marmousi/metadata.py
misfit_toys/data/marmousi/deepwave_example/__init__.py
misfit_toys/data/marmousi/deepwave_example/factory.py
misfit_toys/data/marmousi/deepwave_example/shots16/__init__.py
misfit_toys/data/marmousi/deepwave_example/shots16/factory.py
misfit_toys/data/marmousi/deepwave_example/shots16/twolayer/factory.py
misfit_toys/data/marmousi/deepwave_example/shots16/twolayer_strong/__init__.py
misfit_toys/data/marmousi/deepwave_example/shots16/twolayer_strong/factory.py
misfit_toys/data/marmousi/deepwave_example/shots16/twolayer_verystrong/__init__.py
misfit_toys/data/marmousi/deepwave_example/shots16/twolayer_verystrong/factory.py
misfit_toys/data/marmousi2/__init__.py
misfit_toys/data/marmousi2/factory.py
misfit_toys/data/marmousi2/metadata.py
misfit_toys/data/marmousi2/medium/__init__.py
misfit_toys/data/marmousi2/medium/factory.py
misfit_toys/data/marmousi2/tiny/__init__.py
misfit_toys/data/marmousi2/tiny/factory.py
misfit_toys/examples/__init__.py
misfit_toys/examples/exhaustive/main.py
misfit_toys/examples/forward/twolayer/main.py
misfit_toys/examples/hydra/helpers.py
misfit_toys/examples/hydra/main.py
misfit_toys/examples/hydra/out/tmp.py
misfit_toys/examples/marmousi/validate.py
misfit_toys/examples/marmousi/alan/forward.py
misfit_toys/examples/marmousi/alan/fwi.py
misfit_toys/examples/marmousi/alan/fwi_parallel.py
IslandOfMisfitToys-0.5.0.dist-info/METADATA
IslandOfMisfitToys-0.5.0.dist-info/WHEEL
IslandOfMisfitToys-0.5.0.dist-info/top_level.txt
IslandOfMisfitToys-0.5.0.dist-info/RECORD
