Metadata-Version: 2.1
Name: IslandOfMisfitToys
Version: 0.5.0
Summary: A suite of misfit functions to test FWI
Home-page: https://github.com/tmasthay/IslandOfMisfitToys
Author: Tyler Masthay and Yiran Shen
Author-email: tyler@ices.utexas.edu
Classifier: Programming Language :: Python :: 3
Classifier: License :: OSI Approved :: MIT License
Classifier: Operating System :: OS Independent
Classifier: Intended Audience :: Science/Research
Classifier: Topic :: Scientific/Engineering
Requires-Python: >=3.9
Requires-Dist: black >=23.9.1
Requires-Dist: deepwave >=0.0.19
Requires-Dist: imageio >=2.31.1
Requires-Dist: masthay-helpers >=0.2.94
Requires-Dist: matplotlib >=3.7.2
Requires-Dist: matplotlib-inline >=0.1.6
Requires-Dist: numpy >=1.25.2
Requires-Dist: obspy >=1.4.0
Requires-Dist: pynvml >=11.5.0
Requires-Dist: pytest >=8.0.1
Requires-Dist: python-json-logger >=2.0.7
Requires-Dist: requests >=2.31.0
Requires-Dist: returns >=0.22.0
Requires-Dist: rich >=13.6.0
Requires-Dist: scipy >=1.11.1
Requires-Dist: setuptools >=68.0.0
Requires-Dist: torch >=2.0.1
Requires-Dist: torchaudio >=2.0.2
